shortlib/__init__.py
Shortlib-0.0.0.dist-info/LICENSE
Shortlib-0.0.0.dist-info/METADATA
Shortlib-0.0.0.dist-info/NOTICE
Shortlib-0.0.0.dist-info/WHEEL
Shortlib-0.0.0.dist-info/top_level.txt
Shortlib-0.0.0.dist-info/RECORD
